nugget/__init__.py
nugget-0.0.0.dist-info/LICENSE
nugget-0.0.0.dist-info/METADATA
nugget-0.0.0.dist-info/WHEEL
nugget-0.0.0.dist-info/top_level.txt
nugget-0.0.0.dist-info/RECORD
