Metadata-Version: 2.1
Name: nugget
Version: 0.0.0
License-File: LICENSE
Provides-Extra: dev
Requires-Dist: build ; extra == 'dev'
Requires-Dist: black ; extra == 'dev'
Requires-Dist: isort ; extra == 'dev'
Requires-Dist: pre-commit ; extra == 'dev'
Requires-Dist: pylint ; extra == 'dev'
Requires-Dist: flake8 ; extra == 'dev'
